TGenTools-1.0.0rc2.data/scripts/tgentools
tgentools/__init__.py
tgentools/_version.py
tgentools/analysis.py
tgentools/edit.py
tgentools/model.py
tgentools/util.py
tgentools/visualization.py
TGenTools-1.0.0rc2.dist-info/LICENSE
TGenTools-1.0.0rc2.dist-info/METADATA
TGenTools-1.0.0rc2.dist-info/WHEEL
TGenTools-1.0.0rc2.dist-info/top_level.txt
TGenTools-1.0.0rc2.dist-info/RECORD
