Metadata-Version: 2.1
Name: TGenTools
Version: 1.0.0rc2
Summary: A utility to analyze and visualize TGen output
Home-page: https://github.com/shadow/tgen/
Author: Rob Jansen
Author-email: UNKNOWN
License: UNKNOWN
Platform: UNKNOWN
